[
  [
    {
      "name": "Queso",
      "price": 100.0
    },
    20
  ],
  [
    {
      "name": "Harina",
      "price": 100.0
    },
    20
  ],
  [
    {
      "name": "Pure de Tomate",
      "price": 100.0
    },
    20
  ],
  [
    {
      "name": "Aceitunas",
      "price": 100.0
    },
    20
  ],
  [
    {
      "name": "Calabresa",
      "price": 100.0
    },
    20
  ],
  [
    {
      "name": "Cebolla",
      "price": 100.0
    },
    20
  ],
  [
    {
      "name": "Rucula",
      "price": 100.0
    },
    20
  ],
  [
    {
      "name": "Jamon Crudo",
      "price": 100.0
    },
    20
  ],
  [
    {
      "name": "Tomate",
      "price": 100.0
    },
    20
  ]
]